skiml_cluster/__about__.py
skiml_cluster/__init__.py
skiml_cluster/__main__.py
skiml_cluster/config.yaml
skiml_cluster/snk.yaml
skiml_cluster/cli/__init__.py
skiml_cluster/workflow/Snakefile
skiml_cluster/workflow/envs/main.yaml
skiml_cluster/workflow/envs/vk.yaml
skiml_cluster-0.0.6.dist-info/METADATA
skiml_cluster-0.0.6.dist-info/WHEEL
skiml_cluster-0.0.6.dist-info/entry_points.txt
skiml_cluster-0.0.6.dist-info/licenses/LICENSE.txt
skiml_cluster-0.0.6.dist-info/RECORD
